holdem_hand_evaluator-0.4.1.dist-info/METADATA
holdem_hand_evaluator-0.4.1.dist-info/WHEEL
holdem_hand_evaluator/__init__.py
holdem_hand_evaluator/holdem_hand_evaluator.abi3.so
holdem_hand_evaluator-0.4.1.dist-info/RECORD
