Metadata-Version: 2.1
Name: holdem_hand_evaluator
Version: 0.4.1
